Division/3_div.v
module div
#(
    parameter DATA_W = 8

)
(
    input [(DATA_W - 1): 0] data,
    output divisibility
);
    localparam NEW_DATA_W = $clog2(DATA_W);
    wire [NEW_DATA_W - 1: 0]      new_data;
    wire [NEW_DATA_W - 1: 0]          even;
    wire [NEW_DATA_W - 1: 0]           odd;

    assign even = data[0] + data[2] + data[4] + data[6];
    assign  odd = data[1] + data[3] + data[5] + data[7];

    assign new_data = (even < odd) ? odd - even: even - odd; 


    // just check if new_data = 0, 3 or 6;
    // div = (~A)(~B)(~C) | AB(~C) | (~A)BC = ~(A | B | C) | B(A ^ B)
    assign divisibility = ~(new_data[0] |  new_data[1] | new_data[2]) | 
                            new_data[1] & (new_data[0] ^ new_data[2]);
endmodule

Division/testbench.v
`timescale 1ns/100ps

module testbench
#(
    parameter DATA_W = 8
)
();

    reg  [DATA_W - 1:0] data;
    reg  clock    =     1'b1;

    wire divisibility;


    always
    begin
        #5 clock = ~clock;
    end

    div div (.data(data), .divisibility(divisibility));

    initial begin
    $dumpfile ("dump.vcd"); $dumpvars;
    end


    initial begin
        
        #10; data = 8'd0; #10;
        $display("if data = %d, divisibility = %d", data, divisibility);
        
        #10; data = 8'd1; #10;
        $display("if data = %d, divisibility = %d", data, divisibility);
        
        #10; data = 8'd3; #10;
        $display("if data = %d, divisibility = %d", data, divisibility);
        
        #10; data = 8'd8; #10;
        $display("if data = %d, divisibility = %d", data, divisibility);
        
        #10; data = 8'd11; #10;
        $display("if data = %d, divisibility = %d", data, divisibility);
        
        #10; data = 8'd15; #10;
        $display("if data = %d, divisibility = %d", data, divisibility);
        
        #10; data = 8'd171; #10;
        $display("if data = %d, divisibility = %d", data, divisibility);
        
        #10; data = 8'd255; #10;
        $display("if data = %d, divisibility = %d", data, divisibility);
        
        #10; data = 8'd115; #10;
        $display("if data = %d, divisibility = %d", data, divisibility);
        
        #10; data = 8'd222; #10;
        $display("if data = %d, divisibility = %d", data, divisibility);

        $finish;
    end
endmodule

Division/dump.vcd
$date
	Sat Apr 20 19:33:42 2024
$end
$version
	Icarus Verilog
$end
$timescale
	100ps
$end
$scope module testbench $end
$var wire 1 ! divisibility $end
$var reg 1 " clock $end
$var reg 8 # data [7:0] $end
$scope module div $end
$var wire 8 $ data [7:0] $end
$var wire 1 ! divisibility $end
$var wire 3 % odd [2:0] $end
$var wire 3 & new_data [2:0] $end
$var wire 3 ' even [2:0] $end
$upscope $end
$upscope $end
$enddefinitions $end
#0
$dumpvars
bx '
bx &
bx %
bx $
bx #
1"
x!
$end
#50
0"
#100
1!
b0 &
b0 '
b0 %
1"
b0 #
b0 $
#150
0"
#200
1"
#250
0"
#300
0!
b1 &
b1 '
1"
b1 #
b1 $
#350
0"
#400
1"
#450
0"
#500
1!
b0 &
b1 %
1"
b11 #
b11 $
#550
0"
#600
1"
#650
0"
#700
0!
b1 &
b0 '
b1 %
1"
b1000 #
b1000 $
#750
0"
#800
1"
#850
0"
#900
b1 '
b10 %
1"
b1011 #
b1011 $
#950
0"
#1000
1"
#1050
0"
#1100
1!
b0 &
b10 '
1"
b1111 #
b1111 $
#1150
0"
#1200
1"
#1250
0"
#1300
b11 &
b1 '
b100 %
1"
b10101011 #
b10101011 $
#1350
0"
#1400
1"
#1450
0"
#1500
1!
b0 &
b100 '
1"
b11111111 #
b11111111 $
#1550
0"
#1600
1"
#1650
0"
#1700
0!
b1 &
b11 '
b10 %
1"
b1110011 #
b1110011 $
#1750
0"
#1800
1"
#1850
0"
#1900
1!
b0 &
b11 '
b11 %
1"
b11011110 #
b11011110 $
