Memory/memory.v
module memory
#(
    parameter    DATA_W = 8,
    parameter  MEM_SIZE = 6,
    parameter ADDR_SIZE = $clog2(MEM_SIZE)
)

(
    input write,
    input  read,
    input clock,

    output reg [(DATA_W    - 1): 0] dataout,
    input      [(DATA_W    - 1): 0]  datain,
    input      [(ADDR_SIZE - 1): 0]  addr_w,
    input      [(ADDR_SIZE - 1): 0]  addr_r
);

    reg [(MEM_SIZE - 1): 0] memory [(DATA_W - 1): 0];

    always @(posedge clock)
    begin 
    
        if (read & write)
        begin
            if (addr_r < MEM_SIZE)
            begin
                dataout <= memory[addr_r];
                memory[addr_w]  <= datain;
            end
            else
                dataout <= 0;
        end


        else if (read) 
        begin
            if (addr_r  <  MEM_SIZE)
                dataout <= memory[addr_r];
            else
                dataout <= 0;
        end


        else if (write)
        begin
            if (addr_w < MEM_SIZE)
                memory[addr_w]  <= datain;
        end

    end
endmodule

Memory/test.v
`timescale 1ns/100ps
module testbench();
  
	wire [7:0] DATAOUT;
  	reg  [2:0] addr_r, addr_w;
  	reg wn, rn;
  	reg [7:0] DATAIN;  
	
	reg clock = 1'b1;
	always begin
		#5 clock = ~clock;
	end

  	memory memory ( .write(wn), .read(rn), .clock(clock), .dataout(DATAOUT), .datain(DATAIN), .addr_w(addr_w), .addr_r(addr_r) );
  
	initial begin 
		$dumpfile("dump.vcd"); $dumpvars;
	end
	
	initial begin
		wn = 1; rn = 0; #10;
		addr_w = 3'd0; DATAIN = 8'h0;
	       
	       #10; addr_w = 3'd5; DATAIN = 8'h5;

	       #10; wn = 1; rn = 1;
	       #10; addr_w = 3'd7; DATAIN = 8'h4;
	       #20; addr_w = 3'd5; addr_r = 3'd5; DATAIN = 8'h8;
	       #10; addr_w = 3'd4; addr_r = 3'd0; DATAIN = 8'h10;
	       
	       #10; wn = 1; rn = 0;
	       #20; addr_w = 3'd3; DATAIN = 8'h40;
	       #10; addr_w = 3'd1; DATAIN = 8'h70;
	       #10; addr_w = 3'd2; DATAIN = 8'h4;
	       
	       wn = 0; rn = 1;
	       #20; addr_r = 3'd0;
	       #10; addr_r = 3'd5;
	       #10; addr_r = 3'd2;
	       #10; addr_r = 3'd4;
	       #10; addr_r = 3'd1;
	       #10; addr_r = 3'd3;
	       #10; addr_r = 3'd7;
	       #10; $finish;
       end

endmodule

Memory/dump.vcd
$date
	Thu Apr 18 16:52:23 2024
$end
$version
	Icarus Verilog
$end
$timescale
	100ps
$end
$scope module testbench $end
$var wire 8 ! DATAOUT [7:0] $end
$var reg 8 " DATAIN [7:0] $end
$var reg 3 # addr_r [2:0] $end
$var reg 3 $ addr_w [2:0] $end
$var reg 1 % clock $end
$var reg 1 & rn $end
$var reg 1 ' wn $end
$scope module memory $end
$var wire 3 ( addr_r [2:0] $end
$var wire 3 ) addr_w [2:0] $end
$var wire 1 % clock $end
$var wire 8 * datain [7:0] $end
$var wire 1 & read $end
$var wire 1 ' write $end
$var reg 8 + dataout [7:0] $end
$upscope $end
$upscope $end
$enddefinitions $end
#0
$dumpvars
bx +
bx *
bx )
bx (
1'
0&
1%
bx $
bx #
bx "
bx !
$end
#50
0%
#100
1%
b0 "
b0 *
b0 $
b0 )
#150
0%
#200
1%
b101 "
b101 *
b101 $
b101 )
#250
0%
#300
b0 !
b0 +
1%
1&
#350
0%
#400
1%
b100 "
b100 *
b111 $
b111 )
#450
0%
#500
1%
#550
0%
#600
b101 !
b101 +
1%
b1000 "
b1000 *
b101 #
b101 (
b101 $
b101 )
#650
0%
#700
b0 !
b0 +
1%
b10000 "
b10000 *
b0 #
b0 (
b100 $
b100 )
#750
0%
#800
1%
0&
#850
0%
#900
1%
#950
0%
#1000
1%
b1000000 "
b1000000 *
b11 $
b11 )
#1050
0%
#1100
1%
b1110000 "
b1110000 *
b1 $
b1 )
#1150
0%
#1200
1%
1&
0'
b100 "
b100 *
b10 $
b10 )
#1250
0%
#1300
1%
#1350
0%
#1400
1%
#1450
0%
#1500
b1000 !
b1000 +
1%
b101 #
b101 (
#1550
0%
#1600
b0xxxxxx !
b0xxxxxx +
1%
b10 #
b10 (
#1650
0%
#1700
b10000 !
b10000 +
1%
b100 #
b100 (
#1750
0%
#1800
b110000 !
b110000 +
1%
b1 #
b1 (
#1850
0%
#1900
b0 !
b0 +
1%
b11 #
b11 (
#1950
0%
#2000
1%
b111 #
b111 (
