Memory/memory.v
module memory
#(
    parameter    DATA_W = 8,
    parameter  MEM_SIZE = 6,
    parameter ADDR_SIZE = $clog2(MEM_SIZE)
)

(
    input write,
    input  read,
    input clock,

    output reg [(DATA_W    - 1): 0] dataout,
    input      [(DATA_W    - 1): 0]  datain,
    input      [(ADDR_SIZE - 1): 0]  addr_w,
    input      [(ADDR_SIZE - 1): 0]  addr_r
);

    reg [(MEM_SIZE - 1): 0] memory [(DATA_W - 1): 0];

    always @(posedge clock)
    begin 
    
        if (read & write)
        begin
            if (addr_r < MEM_SIZE)
            begin
                dataout <= memory[addr_r];
                memory[addr_w]  <= datain;
            end
            else
                dataout <= 0;
        end


        else if (read) 
        begin
            if (addr_r  <  MEM_SIZE)
                dataout <= memory[addr_r];
            else
                dataout <= 0;
        end


        else if (write)
        begin
            if (addr_w < MEM_SIZE)
                memory[addr_w]  <= datain;
        end

    end
endmodule

Memory/testbench.v
`timescale 1ns/100ps
module testbench();
  
	wire [7:0] dataout;
  	reg  [7:0]  datain;  
  	reg  [2:0]  addr_r;
  	reg  [2:0]  addr_w;
  	reg          write;
  	reg           read;
	reg  clock =  1'b1;
    

	always begin
		#5 clock = ~clock;
	end

  	memory memory ( .write(write), .read(read), .clock(clock), .dataout(dataout), .datain(datain), .addr_w(addr_w), .addr_r(addr_r) );
  
	initial begin 
		$dumpfile("dump.vcd"); $dumpvars;
	end
	
	initial begin
		#10; write  =    1;   read =    0;
		#20; addr_w = 3'd0; datain = 8'h0;
        #10; addr_w = 3'd5; datain = 8'h5;
        #20; addr_w = 3'd5; addr_r = 3'd5; datain = 8'h8;
        #10; addr_r = 3'd0;

        #10; write  =    1;   read =    1;
        #10; addr_w = 3'd7; datain = 8'h4; // invalid adress
        #20; addr_w = 3'd5; addr_r = 3'd5; datain = 8'h8; // same addr
        #10; addr_w = 3'd4; addr_r = 3'd0; datain = 8'h10; // different addr
        #10; addr_r = 3'd4;

        #10; write  =    1;   read =    0;
        #20; addr_w = 3'd6; addr_r = 3'd6; datain = 8'h9;
        #20; addr_w = 3'd6; addr_r = 3'd7; datain = 8'h10;
        #20; addr_w = 3'd3; datain = 8'h40;
        #10; addr_w = 3'd1; datain = 8'h70;
        #10; addr_w = 3'd2; datain = 8'h4;
        #10; addr_r = 3'd1;
        #10; addr_r = 3'd2;
        
        #10; write  =    0;   read =     0;
        #20; addr_w = 3'd5; addr_r = 3'd5; datain = 8'h8; // same addr
        #10; addr_w = 3'd4; addr_r = 3'd0; datain = 8'h10; // different addr
        #10; addr_w = 3'd3; datain = 8'h40;
        #10; addr_w = 3'd1; datain = 8'h70;
        #10; addr_w = 3'd2; datain = 8'h4;
        #10; addr_r = 3'd7;
        #10; addr_r = 3'd3;

        #10; write  =    0; read   =    1;
        #20; addr_w = 3'd5; addr_r = 3'd5; datain = 8'h8; // same addr
        #10; addr_w = 3'd4; addr_r = 3'd0; datain = 8'h10; // different addr
        #10; addr_w = 3'd3; datain = 8'h40;
        #10; addr_r = 3'd0;
        #10; addr_r = 3'd5;
        #10; addr_w = 3'd1; datain = 8'h70;
        #10; addr_w = 3'd2; datain = 8'h4;
        #10; addr_r = 3'd2;
        #10; addr_r = 3'd4;
        #10; addr_r = 3'd1;
        #10; addr_r = 3'd3;
        #10; addr_r = 3'd7; // invalid adress
        #10; $finish;
    end

endmodule

Memory/dump.vcd
$date
	Sat Apr 20 20:26:49 2024
$end
$version
	Icarus Verilog
$end
$timescale
	100ps
$end
$scope module testbench $end
$var wire 8 ! dataout [7:0] $end
$var reg 3 " addr_r [2:0] $end
$var reg 3 # addr_w [2:0] $end
$var reg 1 $ clock $end
$var reg 8 % datain [7:0] $end
$var reg 1 & read $end
$var reg 1 ' write $end
$scope module memory $end
$var wire 3 ( addr_r [2:0] $end
$var wire 3 ) addr_w [2:0] $end
$var wire 1 $ clock $end
$var wire 8 * datain [7:0] $end
$var wire 1 & read $end
$var wire 1 ' write $end
$var reg 8 + dataout [7:0] $end
$upscope $end
$upscope $end
$enddefinitions $end
#0
$dumpvars
bx +
bx *
bx )
bx (
x'
x&
bx %
1$
bx #
bx "
bx !
$end
#50
0$
#100
1$
0&
1'
#150
0$
#200
1$
#250
0$
#300
1$
b0 %
b0 *
b0 #
b0 )
#350
0$
#400
1$
b101 %
b101 *
b101 #
b101 )
#450
0$
#500
1$
#550
0$
#600
1$
b1000 %
b1000 *
b101 "
b101 (
#650
0$
#700
1$
b0 "
b0 (
#750
0$
#800
b0 !
b0 +
1$
1&
#850
0$
#900
1$
b100 %
b100 *
b111 #
b111 )
#950
0$
#1000
1$
#1050
0$
#1100
b1000 !
b1000 +
1$
b1000 %
b1000 *
b101 "
b101 (
b101 #
b101 )
#1150
0$
#1200
b0 !
b0 +
1$
b10000 %
b10000 *
b0 "
b0 (
b100 #
b100 )
#1250
0$
#1300
b10000 !
b10000 +
1$
b100 "
b100 (
#1350
0$
#1400
1$
0&
#1450
0$
#1500
1$
#1550
0$
#1600
1$
b1001 %
b1001 *
b110 "
b110 (
b110 #
b110 )
#1650
0$
#1700
1$
#1750
0$
#1800
1$
b10000 %
b10000 *
b111 "
b111 (
#1850
0$
#1900
1$
#1950
0$
#2000
1$
b1000000 %
b1000000 *
b11 #
b11 )
#2050
0$
#2100
1$
b1110000 %
b1110000 *
b1 #
b1 )
#2150
0$
#2200
1$
b100 %
b100 *
b10 #
b10 )
#2250
0$
#2300
1$
b1 "
b1 (
#2350
0$
#2400
1$
b10 "
b10 (
#2450
0$
#2500
1$
0'
#2550
0$
#2600
1$
#2650
0$
#2700
1$
b1000 %
b1000 *
b101 "
b101 (
b101 #
b101 )
#2750
0$
#2800
1$
b10000 %
b10000 *
b0 "
b0 (
b100 #
b100 )
#2850
0$
#2900
1$
b1000000 %
b1000000 *
b11 #
b11 )
#2950
0$
#3000
1$
b1110000 %
b1110000 *
b1 #
b1 )
#3050
0$
#3100
1$
b100 %
b100 *
b10 #
b10 )
#3150
0$
#3200
1$
b111 "
b111 (
#3250
0$
#3300
1$
b11 "
b11 (
#3350
0$
#3400
b0 !
b0 +
1$
1&
#3450
0$
#3500
1$
#3550
0$
#3600
b1000 !
b1000 +
1$
b1000 %
b1000 *
b101 "
b101 (
b101 #
b101 )
#3650
0$
#3700
b0 !
b0 +
1$
b10000 %
b10000 *
b0 "
b0 (
b100 #
b100 )
#3750
0$
#3800
1$
b1000000 %
b1000000 *
b11 #
b11 )
#3850
0$
#3900
1$
#3950
0$
#4000
b1000 !
b1000 +
1$
b101 "
b101 (
#4050
0$
#4100
1$
b1110000 %
b1110000 *
b1 #
b1 )
#4150
0$
#4200
1$
b100 %
b100 *
b10 #
b10 )
#4250
0$
#4300
b100 !
b100 +
1$
b10 "
b10 (
#4350
0$
#4400
b10000 !
b10000 +
1$
b100 "
b100 (
#4450
0$
#4500
b110000 !
b110000 +
1$
b1 "
b1 (
#4550
0$
#4600
b0 !
b0 +
1$
b11 "
b11 (
#4650
0$
#4700
1$
b111 "
b111 (
